LICENSE
MANIFEST.in
README.md
requirements.txt
setup.py
bin/rolemodel
rolemodel/__init__.py
rolemodel/_version
rolemodel/group.py
rolemodel/role.py
rolemodel/stack.py
rolemodel.egg-info/PKG-INFO
rolemodel.egg-info/SOURCES.txt
rolemodel.egg-info/dependency_links.txt
rolemodel.egg-info/requires.txt
rolemodel.egg-info/top_level.txt
sample/config.yml
sample/group.cf
sample/roles.cf
sample/users.yml