Metadata-Version: 1.1
Name: rolemodel
Version: 0.1.0
Summary: A tool to help manage cross-account roles in AWS
Home-page: https://github.com/scopely-devops/rolemodel
Author: Mitch Garnaat
Author-email: mitch@garnaat.com
License: Apache License
